Metadata-Version: 1.1
Name: pdLSR
Version: 0.3.3
Summary: pdLSR: Pandas-aware least squares regression.
Home-page: https://github.com/mlgill/pdLSR
Author: Michelle Gill
Author-email: michelle@michellelynngill.com
License: BSD (3-clause)
Download-URL: https://github.com/mlgill/pdLSR
Platform: UNKNOWN
Classifier: Intended Audience :: Science/Research
Classifier: Programming Language :: Python :: 2.7
Classifier: Programming Language :: Python :: 3.4
Classifier: Programming Language :: Python :: 3.5
Classifier: License :: OSI Approved :: BSD License
Classifier: Topic :: Scientific/Engineering :: Chemistry
Classifier: Topic :: Scientific/Engineering :: Visualization
Classifier: Operating System :: POSIX
Classifier: Operating System :: Unix
Classifier: Operating System :: MacOS
